LICENSE.txt
README.md
setup.py
onepackage/__init__.py
onepackage/__main__.py
onepackage/cifrar.py
onepackage/descifrar.py
onepackage/validarMensaje.py
onepackage.egg-info/PKG-INFO
onepackage.egg-info/SOURCES.txt
onepackage.egg-info/dependency_links.txt
onepackage.egg-info/entry_points.txt
onepackage.egg-info/top_level.txt