Metadata-Version: 2.1
Name: onepackage
Version: 0.0.2
Summary: Permite cifrar y descifrar texto
Home-page: https://github.com/Ange1D/ONEPackage
Author: Ange1D
Author-email: ange1d.contact0@gmail.com
License: MIT
Keywords: cifrar,descifrar,ONE,Oracle Next Education
Platform: UNKNOWN
Classifier: Development Status :: 3 - Alpha
Classifier: Intended Audience :: Developers
Classifier: Topic :: Software Development :: Build Tools
Classifier: License :: OSI Approved :: MIT License
Classifier: Programming Language :: Python :: 3
License-File: LICENSE.txt
